{
    "forge_marker":1,
    "defaults":{
        "textures":{
            "particle":"enderio:blocks/blockSoulMachineBottom"
        }
    },
    "variants":{
        "render":{
			"defaults":{ "model":"enderio:transform/block" },
			"auto":{ "model":"enderio:null" },
            "front":{          "submodel":{ "front":{ "model":"enderio:poweredSpawner" } }, "y":0 },
            "front_east":{     "submodel":{ "front":{ "model":"enderio:poweredSpawner" } }, "y":90 },
            "front_south":{    "submodel":{ "front":{ "model":"enderio:poweredSpawner" } }, "y":180 },
            "front_west":{     "submodel":{ "front":{ "model":"enderio:poweredSpawner" } }, "y":270 },
            "front_on":{       "submodel":{ "front":{ "model":"enderio:poweredSpawner" } }, "y":0, "textures": { "1": "enderio:blocks/blockPoweredSpawnerActive" } },
            "front_on_east":{  "submodel":{ "front":{ "model":"enderio:poweredSpawner" } }, "y":90, "textures": { "1": "enderio:blocks/blockPoweredSpawnerActive" } },
            "front_on_south":{ "submodel":{ "front":{ "model":"enderio:poweredSpawner" } }, "y":180,   "textures": { "1": "enderio:blocks/blockPoweredSpawnerActive" } },
            "front_on_west":{  "submodel":{ "front":{ "model":"enderio:poweredSpawner" } }, "y":270,  "textures": { "1": "enderio:blocks/blockPoweredSpawnerActive" } }
        }
    }
}