{
    "forge_marker": 1,
    "defaults": {
        "model": "enderio:cube"
    },
  "variants":{
    "type":{
      "type00":             { "textures": {
        "particle": "enderio:items/item_machine_chassi",
        "bottom":   "enderio:items/item_machine_chassi",
        "top":      "enderio:items/item_machine_chassi",
        "side":     "enderio:items/item_machine_chassi"
      }, "model":   "enderio:hollow_cube" },
      "type01":             { "textures": { "particle": "enderio:blocks/block_machine_bottom", "all": "enderio:blocks/block_machine_bottom" } },
      "type02":             { "textures": { "particle": "enderio:blocks/block_machine_top",    "all": "enderio:blocks/block_machine_top" } },
      "type03":             { "textures": { "particle": "enderio:blocks/block_machine_side",   "all": "enderio:blocks/block_machine_side" } },
      "type04":             { "textures": { "particle": "enderio:blocks/block_machine_back",   "all": "enderio:blocks/block_machine_back" } },
      "type05":             { "textures": {
        "particle": "enderio:blocks/block_machine_bottom",
        "bottom":   "enderio:blocks/block_machine_bottom",
        "top":      "enderio:blocks/block_machine_top",
        "side":     "enderio:blocks/block_machine_side"
      }, "model":   "enderio:sided_cube" },
      "type06":             { "textures": {
        "particle": "enderio:blocks/block_machine_bottom",
        "bottom":   "enderio:blocks/block_machine_bottom",
        "top":      "enderio:blocks/block_machine_top",
        "side":     "enderio:blocks/block_machine_back"
      }, "model":   "enderio:sided_cube" },
      "type07":             { "textures": { "particle": "enderio:blocks/block_soul_machine_bottom", "all": "enderio:blocks/block_soul_machine_bottom" } },
      "type08":             { "textures": { "particle": "enderio:blocks/block_soul_machine_top",    "all": "enderio:blocks/block_soul_machine_top" } },
      "type09":             { "textures": { "particle": "enderio:blocks/block_soul_machine_side",   "all": "enderio:blocks/block_soul_machine_side" } },
      "type10":             { "textures": { "particle": "enderio:blocks/block_soul_machine_back",   "all": "enderio:blocks/block_soul_machine_back" } },
      "type11":             { "textures": {
        "particle": "enderio:blocks/block_soul_machine_bottom",
        "bottom":   "enderio:blocks/block_soul_machine_bottom",
        "top":      "enderio:blocks/block_soul_machine_top",
        "side":     "enderio:blocks/block_soul_machine_side"
      }, "model":   "enderio:sided_cube" },
      "type12":             { "textures": {
        "particle": "enderio:blocks/block_soul_machine_bottom",
        "bottom":   "enderio:blocks/block_soul_machine_bottom",
        "top":      "enderio:blocks/block_soul_machine_top",
        "side":     "enderio:blocks/block_soul_machine_back"
      }, "model":   "enderio:sided_cube" },
      "type13":             { "textures": { "particle": "enderio:blocks/block_capacitor_bank_creative", "all": "enderio:blocks/block_capacitor_bank_creative" } },
      "type14":             { "textures": {
        "particle": "enderio:items/item_broken_spawner",
        "bottom":   "enderio:items/item_broken_spawner",
        "top":      "enderio:items/item_broken_spawner",
        "side":     "enderio:items/item_broken_spawner"
      }, "model":   "enderio:hollow_cube" },
      "type15":             { "model": "enderio:null", "textures": { "particle": "enderio:blocks/blank" } }
    }
  }
}
