{
	"forge_marker": 1,
	"defaults": {
		"model": "enderio:cube",
		"textures": {
			"all": "enderio:blocks/electricalSteelBlock"
		}
	},
	"variants": {
		"variant": {
			"electricalsteel": {
				"textures": {
					"all": "enderio:blocks/electricalSteelBlock"
				}
			},
			"energeticalloy": {
				"textures": {
					"all": "enderio:blocks/energeticAlloyBlock"
				}
			},
			"vibrantalloy": {
				"textures": {
					"all": "enderio:blocks/vibrantAlloyBlock"
				}
			},
			"redstonealloy": {
				"textures": {
					"all": "enderio:blocks/redstoneAlloyBlock"
				}
			},
			"conductiveiron": {
				"textures": {
					"all": "enderio:blocks/conductiveIronBlock"
				}
			},
			"pulsatingiron": {
				"textures": {
					"all": "enderio:blocks/pulsatingIronBlock"
				}
			},
			"darksteel": {
				"textures": {
					"all": "enderio:blocks/darkSteelBlock"
				}
			},
			"soularium": {
				"textures": {
					"all": "enderio:blocks/soulariumBlock"
				}
			}
		}
	}
}